byted_overpass_wukong_browser_forum_resource/__init__.py
byted_overpass_wukong_browser_forum_resource-0.0.1.dist-info/METADATA
byted_overpass_wukong_browser_forum_resource-0.0.1.dist-info/WHEEL
byted_overpass_wukong_browser_forum_resource-0.0.1.dist-info/top_level.txt
byted_overpass_wukong_browser_forum_resource-0.0.1.dist-info/RECORD
